Templates/__init__.py
rmldoc/__init__.py
rmldoc/__main__.py
rmldoc/queries.py
rmldoc/utils.py
rmldoc/Templates/TriplesMap.md
rmldoc/Templates/__init__.py
rmldoc/Templates/base.md
rmldoc/Templates/diagram.md
rmldoc/Templates/function.md
rmldoc/Templates/named_graph.md
rmldoc/Templates/predicate_object.md
rmldoc/Templates/rmd.md
rmldoc/Templates/source.md
rmldoc/Templates/subject.md
rmldoc-0.1.8.dist-info/LICENSE
rmldoc-0.1.8.dist-info/METADATA
rmldoc-0.1.8.dist-info/WHEEL
rmldoc-0.1.8.dist-info/entry_points.txt
rmldoc-0.1.8.dist-info/top_level.txt
rmldoc-0.1.8.dist-info/RECORD
