Metadata-Version: 2.1
Name: rmldoc
Version: 0.1.8
Summary: Rmldoc is a tool that generates documentation of RML mappings
Home-page: https://github.com/oeg-upm/rmldoc
Author: Jhon Toledo
Author-email: ja.toledo@upm.es
Classifier: License :: OSI Approved :: Apache Software License
Classifier: Development Status :: 3 - Alpha
Classifier: Programming Language :: Python
Classifier: Programming Language :: Python :: 3.8
Classifier: Intended Audience :: Science/Research
Classifier: Operating System :: Unix
Requires-Python: >=3.8
License-File: LICENSE
Requires-Dist: rdflib >=6.0.2
Requires-Dist: Jinja2 >=3.1.2
Requires-Dist: yatter >=1.1.2
